drf_buzz/__init__.py
drf_buzz/utils.py
test_project/__init__.py
test_project/manage.py
test_project/settings.py
test_project/settings_local.py
test_project/urls.py
test_project/test_app/__init__.py
test_project/test_app/serializers.py
test_project/test_app/views.py
tests/__init__.py
tests/conftest.py
tests/test_basic.py
tests/test_example.py
tests/test_requests.py
drf_buzz-0.3.1.dist-info/LICENSE
drf_buzz-0.3.1.dist-info/METADATA
drf_buzz-0.3.1.dist-info/WHEEL
drf_buzz-0.3.1.dist-info/top_level.txt
drf_buzz-0.3.1.dist-info/RECORD
