Metadata-Version: 2.1
Name: drf-buzz
Version: 0.3.1
Summary: UNKNOWN
Home-page: https://github.com/adalekin/drf-buzz
Author: Aleksey Dalekin
Author-email: adalekin@gmail.com
License: BSD
Keywords: drf error py-buzz
Platform: any
Classifier: Development Status :: 3 - Alpha
Classifier: License :: OSI Approved :: BSD License
Classifier: Topic :: System :: Distributed Computing
Classifier: Intended Audience :: Developers
Classifier: Programming Language :: Python
Classifier: Programming Language :: Python :: 3.5
Classifier: Programming Language :: Python :: 3.6
Classifier: Programming Language :: Python :: 3.7
Classifier: Programming Language :: Python :: Implementation :: CPython
Classifier: Operating System :: OS Independent
Requires-Dist: Django (<2.2,>=1.11)
Requires-Dist: djangorestframework (<3.10,>=3.8)
Requires-Dist: py-buzz (>=0.3.6)
Requires-Dist: requests (>=2.21.0)
